vevde_security_utils/__init__.py
vevde_security_utils/crypt/__init__.py
vevde_security_utils/crypt/aes.py
vevde_security_utils/crypt/camellia.py
vevde_security_utils/crypt/file_ops.py
vevde_security_utils/crypt/hmac.py
vevde_security_utils/crypt/settings.py
vevde_security_utils/crypt/signatures.py
vevde_security_utils-2.2.0.dist-info/licenses/LICENSE
vevde_security_utils-2.2.0.dist-info/METADATA
vevde_security_utils-2.2.0.dist-info/WHEEL
vevde_security_utils-2.2.0.dist-info/top_level.txt
vevde_security_utils-2.2.0.dist-info/RECORD
