Metadata-Version: 2.4
Name: vevde_security_utils
Version: 2.2.0
Summary: A reusable library of security functions and tools for Python web frameworks
Author-email: "Harisankar Krishna Swamy @ Vevde" <harisankar.krishna@outlook.com>
Project-URL: Homepage, https://github.com/harisankar-krishna-swamy/django_cacheable_model.git
Classifier: Programming Language :: Python :: 3
Classifier: License :: OSI Approved :: Apache Software License
Classifier: Operating System :: OS Independent
Requires-Python: >=3.7.4
License-File: LICENSE
Requires-Dist: cryptography>=3.4.8
Dynamic: license-file
